{
    "fileTypes": [
        "ini"
    ],
    "name": "droid",
    "patterns": [
        {
            "include": "#main"
        }
    ],
    "scopeName": "source.droid",
    "uuid": "",
    "repository": {
        "main": {
            "patterns": [



                {
                    "include": "#basics"
                },
                {
                    "include": "#controllers"
                },



                {
                    "include": "#compare"
                },
                {
                    "include": "#chord"
                },
                {
                    "include": "#buttongroup"
                },
                {
                    "include": "#midiout"
                },
                {
                    "include": "#burst"
                },
                {
                    "include": "#clocktool"
                },
                {
                    "include": "#lfo"
                },
                {
                    "include": "#random"
                },
                {
                    "include": "#arpeggio"
                },
                {
                    "include": "#sample"
                },
                {
                    "include": "#fold"
                },
                {
                    "include": "#droid"
                },
                {
                    "include": "#superjust"
                },
                {
                    "include": "#sequencer"
                },
                {
                    "include": "#switchedpot"
                },
                {
                    "include": "#matrixmixer"
                },
                {
                    "include": "#slew"
                },
                {
                    "include": "#quantizer"
                },
                {
                    "include": "#nudge"
                },
                {
                    "include": "#calibrator"
                },
                {
                    "include": "#motoquencer"
                },
                {
                    "include": "#contour"
                },
                {
                    "include": "#notebuttons"
                },
                {
                    "include": "#adc"
                },
                {
                    "include": "#crossfader"
                },
                {
                    "include": "#spring"
                },
                {
                    "include": "#explin"
                },
                {
                    "include": "#minifonion"
                },
                {
                    "include": "#pot"
                },
                {
                    "include": "#math"
                },
                {
                    "include": "#euklid"
                },
                {
                    "include": "#notchedpot"
                },
                {
                    "include": "#dac"
                },
                {
                    "include": "#fourstatebutton"
                },
                {
                    "include": "#bernoulli"
                },
                {
                    "include": "#transient"
                },
                {
                    "include": "#octave"
                },
                {
                    "include": "#timing"
                },
                {
                    "include": "#midithrough"
                },
                {
                    "include": "#copy"
                },
                {
                    "include": "#midifileplayer"
                },
                {
                    "include": "#cvlooper"
                },
                {
                    "include": "#button"
                },
                {
                    "include": "#mixer"
                },
                {
                    "include": "#queue"
                },
                {
                    "include": "#midiin"
                },
                {
                    "include": "#switch"
                },
                {
                    "include": "#togglebutton"
                },
                {
                    "include": "#triggerdelay"
                },
                {
                    "include": "#motorfader"
                },
                {
                    "include": "#logic"
                },
                {
                    "include": "#algoquencer"
                },
                {
                    "include": "#illegals"
                }
            ]
        },
        "basics": {
            "patterns": [
                {
                    "include": "#region"
                },
                {
                    "include": "#comment"
                },
                {
                    "include": "#numeric"
                },
                {
                    "include": "#ioregister"
                },
                {
                    "include": "#cable"
                },
                {
                    "include": "#punct"
                }
            ]
        },
        "region":{
            "patterns": [
                {
                    "match": "(\\s*//\\s*#?region.*)",
                    "name": "start.region.droid"
                },
                {
                    "match": "(\\s*//\\s*#?endregion.*)",
                    "name": "end.region.droid"
                }
            ]
        },
        "comment": {
            "patterns": [
                {
                    "match": "(//.*)",
                    "name": "comment.droid"
                },
                {
                    "match": "(#.*)",
                    "name": "comment.droid"
                }
            ]
        },
        "numeric": {
            "patterns": [
                {
                    "match": "(on|off|-?([0-9]|[1-9][0-9]*)(.[0-9]+)?[V\\x{0025}]?)",
                    "name": "constant.numeric.droid"
                }
            ]
        },
        "ioregister": {
            "patterns": [
                {
                    "match": "([ionION][1-8])",
                    "name": "support.constant.droid"
                },
                {
                    "match": "([rR](3[0-2]|[1-2]?[0-9]|[0-9]))",
                    "name": "support.constant.droid"
                },
                {
                    "match": "([gG](1[012]|[1-9]))",
                    "name": "support.constant.droid"
                },
                {
                    "match": "([xX]1)",
                    "name": "support.constant.droid"
                },
                {
                    "match": "([lbLB](1[1-6]|[1-9]).([1-2][0-9]|3[0-2]|[1-9]))",
                    "name": "support.constant.droid"
                },
                {
                    "match": "([psPS](1[1-6]|[1-9]).(10|[1-9]))",
                    "name": "support.constant.droid"
                }
            ]
        },
        "cable": {
            "patterns": [
                {
                    "match": "(_[A-Za-z0-9]*)",
                    "name": "constant.other.droid"
                }
            ]
        },
        "punct": {
            "patterns": [
                {
                    "match": "([\\x{003d}\\x{002b}-\\x{002f}\\x{002a}\\s])",
                    "name": "punctuation.droid"
                }
            ]
        },
        "illegals": {
            "patterns": [
                {
                    "match": "([^\\s])",
                    "name": "invalid.droid"
                }
            ]
        },
        "adc": {
            "patterns": [
                {
                    "begin": "(\\[adc\\])",
                    "beginCaptures": {
                        "1": {
                            "name": "support.class.droid"
                        }
                    },
                    "patterns": [
                        {
                            "include": "#inside_adc"
                        }
                    ],
                    "end": "(?=\\[)",
                    "endCaptures": {
                        "1": {
                            "name": "support.class.droid"
                        }
                    }
                }
            ]
        },
        "algoquencer": {
            "patterns": [
                {
                    "begin": "(\\[algoquencer\\])",
                    "beginCaptures": {
                        "1": {
                            "name": "support.class.droid"
                        }
                    },
                    "patterns": [
                        {
                            "include": "#inside_algoquencer"
                        }
                    ],
                    "end": "(?=\\[)",
                    "endCaptures": {
                        "1": {
                            "name": "support.class.droid"
                        }
                    }
                }
            ]
        },
        "arpeggio": {
            "patterns": [
                {
                    "begin": "(\\[arpeggio\\])",
                    "beginCaptures": {
                        "1": {
                            "name": "support.class.droid"
                        }
                    },
                    "patterns": [
                        {
                            "include": "#inside_arpeggio"
                        }
                    ],
                    "end": "(?=\\[)",
                    "endCaptures": {
                        "1": {
                            "name": "support.class.droid"
                        }
                    }
                }
            ]
        },
        
        "bernoulli": {
            "patterns": [
                {
                    "begin": "(\\[bernoulli\\])",
                    "beginCaptures": {
                        "1": {
                            "name": "support.class.droid"
                        }
                    },
                    "patterns": [
                        {
                            "include": "#inside_bernoulli"
                        }
                    ],
                    "end": "(?=\\[)",
                    "endCaptures": {
                        "1": {
                            "name": "support.class.droid"
                        }
                    }
                }
            ]
        },
        "burst": {
            "patterns": [
                {
                    "begin": "(\\[burst\\])",
                    "beginCaptures": {
                        "1": {
                            "name": "support.class.droid"
                        }
                    },
                    "patterns": [
                        {
                            "include": "#inside_burst"
                        }
                    ],
                    "end": "(?=\\[)",
                    "endCaptures": {
                        "1": {
                            "name": "support.class.droid"
                        }
                    }
                }
            ]
        },
        "button": {
            "patterns": [
                {
                    "begin": "(\\[button\\])",
                    "beginCaptures": {
                        "1": {
                            "name": "support.class.droid"
                        }
                    },
                    "patterns": [
                        {
                            "include": "#inside_button"
                        }
                    ],
                    "end": "(?=\\[)",
                    "endCaptures": {
                        "1": {
                            "name": "support.class.droid"
                        }
                    }
                }
            ]
        },
        "buttongroup": {
            "patterns": [
                {
                    "begin": "(\\[buttongroup\\])",
                    "beginCaptures": {
                        "1": {
                            "name": "support.class.droid"
                        }
                    },
                    "patterns": [
                        {
                            "include": "#inside_buttongroup"
                        }
                    ],
                    "end": "(?=\\[)",
                    "endCaptures": {
                        "1": {
                            "name": "support.class.droid"
                        }
                    }
                }
            ]
        },
        "calibrator": {
            "patterns": [
                {
                    "begin": "(\\[calibrator\\])",
                    "beginCaptures": {
                        "1": {
                            "name": "support.class.droid"
                        }
                    },
                    "patterns": [
                        {
                            "include": "#inside_calibrator"
                        }
                    ],
                    "end": "(?=\\[)",
                    "endCaptures": {
                        "1": {
                            "name": "support.class.droid"
                        }
                    }
                }
            ]
        },
        "chord": {
            "patterns": [
                {
                    "begin": "(\\[chord\\])",
                    "beginCaptures": {
                        "1": {
                            "name": "support.class.droid"
                        }
                    },
                    "patterns": [
                        {
                            "include": "#inside_chord"
                        }
                    ],
                    "end": "(?=\\[)",
                    "endCaptures": {
                        "1": {
                            "name": "support.class.droid"
                        }
                    }
                }
            ]
        },
        "clocktool": {
            "patterns": [
                {
                    "begin": "(\\[clocktool\\])",
                    "beginCaptures": {
                        "1": {
                            "name": "support.class.droid"
                        }
                    },
                    "patterns": [
                        {
                            "include": "#inside_clocktool"
                        }
                    ],
                    "end": "(?=\\[)",
                    "endCaptures": {
                        "1": {
                            "name": "support.class.droid"
                        }
                    }
                }
            ]
        },
        
        "compare": {
            "patterns": [
                {
                    "begin": "(\\[compare\\])",
                    "beginCaptures": {
                        "1": {
                            "name": "support.class.droid"
                        }
                    },
                    "patterns": [
                        {
                            "include": "#inside_compare"
                        }
                    ],
                    "end": "(?=\\[)",
                    "endCaptures": {
                        "1": {
                            "name": "support.class.droid"
                        }
                    }
                }
            ]
        },
        "contour": {
            "patterns": [
                {
                    "begin": "(\\[contour\\])",
                    "beginCaptures": {
                        "1": {
                            "name": "support.class.droid"
                        }
                    },
                    "patterns": [
                        {
                            "include": "#inside_contour"
                        }
                    ],
                    "end": "(?=\\[)",
                    "endCaptures": {
                        "1": {
                            "name": "support.class.droid"
                        }
                    }
                }
            ]
        },
        "controllers": {
            "patterns": [
                {
                    "match": "(\\[p2b8\\]|\\[p4b2\\]|\\[b32\\]|\\[p10\\]|\\[s10\\]|\\[m4\\]|\\[x7\\])",
                    "name": "support.class.droid"
                }
            ]
        },
        "copy": {
            "patterns": [
                {
                    "begin": "(\\[copy\\])",
                    "beginCaptures": {
                        "1": {
                            "name": "support.class.droid"
                        }
                    },
                    "patterns": [
                        {
                            "include": "#inside_copy"
                        }
                    ],
                    "end": "(?=\\[)",
                    "endCaptures": {
                        "1": {
                            "name": "support.class.droid"
                        }
                    }
                }
            ]
        },
        "crossfader": {
            "patterns": [
                {
                    "begin": "(\\[crossfader\\])",
                    "beginCaptures": {
                        "1": {
                            "name": "support.class.droid"
                        }
                    },
                    "patterns": [
                        {
                            "include": "#inside_crossfader"
                        }
                    ],
                    "end": "(?=\\[)",
                    "endCaptures": {
                        "1": {
                            "name": "support.class.droid"
                        }
                    }
                }
            ]
        },
        "cvlooper": {
            "patterns": [
                {
                    "begin": "(\\[cvlooper\\])",
                    "beginCaptures": {
                        "1": {
                            "name": "support.class.droid"
                        }
                    },
                    "patterns": [
                        {
                            "include": "#inside_cvlooper"
                        }
                    ],
                    "end": "(?=\\[)",
                    "endCaptures": {
                        "1": {
                            "name": "support.class.droid"
                        }
                    }
                }
            ]
        },
        "dac": {
            "patterns": [
                {
                    "begin": "(\\[dac\\])",
                    "beginCaptures": {
                        "1": {
                            "name": "support.class.droid"
                        }
                    },
                    "patterns": [
                        {
                            "include": "#inside_dac"
                        }
                    ],
                    "end": "(?=\\[)",
                    "endCaptures": {
                        "1": {
                            "name": "support.class.droid"
                        }
                    }
                }
            ]
        },
        "droid": {
            "patterns": [
                {
                    "begin": "(\\[droid\\])",
                    "beginCaptures": {
                        "1": {
                            "name": "support.class.droid"
                        }
                    },
                    "patterns": [
                        {
                            "include": "#inside_droid"
                        }
                    ],
                    "end": "(?=\\[)",
                    "endCaptures": {
                        "1": {
                            "name": "support.class.droid"
                        }
                    }
                }
            ]
        },
        "euklid": {
            "patterns": [
                {
                    "begin": "(\\[euklid\\])",
                    "beginCaptures": {
                        "1": {
                            "name": "support.class.droid"
                        }
                    },
                    "patterns": [
                        {
                            "include": "#inside_euklid"
                        }
                    ],
                    "end": "(?=\\[)",
                    "endCaptures": {
                        "1": {
                            "name": "support.class.droid"
                        }
                    }
                }
            ]
        },
        "explin": {
            "patterns": [
                {
                    "begin": "(\\[explin\\])",
                    "beginCaptures": {
                        "1": {
                            "name": "support.class.droid"
                        }
                    },
                    "patterns": [
                        {
                            "include": "#inside_explin"
                        }
                    ],
                    "end": "(?=\\[)",
                    "endCaptures": {
                        "1": {
                            "name": "support.class.droid"
                        }
                    }
                }
            ]
        },
        "fold": {
            "patterns": [
                {
                    "begin": "(\\[fold\\])",
                    "beginCaptures": {
                        "1": {
                            "name": "support.class.droid"
                        }
                    },
                    "patterns": [
                        {
                            "include": "#inside_fold"
                        }
                    ],
                    "end": "(?=\\[)",
                    "endCaptures": {
                        "1": {
                            "name": "support.class.droid"
                        }
                    }
                }
            ]
        },
        "fourstatebutton": {
            "patterns": [
                {
                    "begin": "(\\[fourstatebutton\\])",
                    "beginCaptures": {
                        "1": {
                            "name": "support.class.droid"
                        }
                    },
                    "patterns": [
                        {
                            "include": "#inside_fourstatebutton"
                        }
                    ],
                    "end": "(?=\\[)",
                    "endCaptures": {
                        "1": {
                            "name": "support.class.droid"
                        }
                    }
                }
            ]
        },
        "inside_adc": {
            "patterns": [
                {
                    "match": "(minimum|maximum|input)",
                    "name": "support.variable.droid"
                },
                {
                    "match": "(bit9|bit8|bit7|bit6|bit5|bit4|bit3|bit2|bit12|bit11|bit10|bit1|bit)",
                    "name": "support.other.variable.droid"
                },
                {
                    "include": "#basics"
                }
            ]
        },
        "inside_algoquencer": {
            "patterns": [
                {
                    "match": "(variation|unmutebutton|selectat|select|savepreset|rollsteps|rollstartvelo|rolls|rollcount|reset|reroll|repeats|prevpattern|preset|pitchresolution|pitchlow|pitchhigh|pitch9|pitch8|pitch7|pitch6|pitch5|pitch4|pitch3|pitch2|pitch16|pitch15|pitch14|pitch13|pitch12|pitch11|pitch10|pitch1|pitch|pattern|offbeats|nextpattern|mutebutton|morphs|loadpreset|lengthbutton|length|gatelength|fills|fillorder|distribution|dejavu|clock|button9|button8|button7|button6|button5|button4|button3|button2|button16|button15|button14|button13|button12|button11|button10|button1|button|branches|alternatebutton|alternatebars|activity|accentlow|accenthigh|accentbutton)",
                    "name": "support.variable.droid"
                },
                {
                    "match": "(unmuteled|trigger|startofbar|rollvelocity|pitch|muteled|morphled|led9|led8|led7|led6|led5|led4|led3|led2|led16|led15|led14|led13|led12|led11|led10|led1|led|gate|fillsled|branch|barled4|barled3|barled2|barled1|barled|accent)",
                    "name": "support.other.variable.droid"
                },
                {
                    "include": "#basics"
                }
            ]
        },
        "inside_arpeggio": {
            "patterns": [
                {
                    "match": "(tuningpitch|tuningmode|transpose|startnote|selectfill5|selectfill4|selectfill3|selectfill2|selectfill1|select9|select7|select5|select3|select13|select11|select1|root|reset|range|pitch|pingpong|pattern|octaves|drop|direction|degree|clock|butterfly)",
                    "name": "support.variable.droid"
                },
                {
                    "match": "(output)",
                    "name": "support.other.variable.droid"
                },
                {
                    "include": "#basics"
                }
            ]
        },
        "inside_bernoulli": {
            "patterns": [
                {
                    "match": "(input|distribution)",
                    "name": "support.variable.droid"
                },
                {
                    "match": "(output2|output1)",
                    "name": "support.other.variable.droid"
                },
                {
                    "include": "#basics"
                }
            ]
        },
        "inside_burst": {
            "patterns": [
                {
                    "match": "(trigger|taptempo|skip|reset|rate|hz|count)",
                    "name": "support.variable.droid"
                },
                {
                    "match": "(output)",
                    "name": "support.other.variable.droid"
                },
                {
                    "include": "#basics"
                }
            ]
        },
        "inside_button": {
            "patterns": [
                {
                    "match": "(value4|value3|value2|value1|value|states|startvalue|selectat|select|reset|onvalue|offvalue|doubleclickmode|button)",
                    "name": "support.variable.droid"
                },
                {
                    "match": "(output|negated|longpress|led|inverted)",
                    "name": "support.other.variable.droid"
                },
                {
                    "include": "#basics"
                }
            ]
        },
        "inside_buttongroup": {
            "patterns": [
                {
                    "match": "(value9|value8|value7|value6|value5|value4|value3|value2|value16|value15|value14|value13|value12|value11|value10|value1|value|selectat|select|minactive|maxactive|button9|button8|button7|button6|button5|button4|button3|button2|button16|button15|button14|button13|button12|button11|button10|button1|button)",
                    "name": "support.variable.droid"
                },
                {
                    "match": "(output|longpress|led9|led8|led7|led6|led5|led4|led3|led2|led16|led15|led14|led13|led12|led11|led10|led1|led|buttonpress)",
                    "name": "support.other.variable.droid"
                },
                {
                    "include": "#basics"
                }
            ]
        },
        "inside_calibrator": {
            "patterns": [
                {
                    "match": "(tunelowtail|tunehightail|tune9|tune8|tune7|tune6|tune5|tune4|tune3|tune2|tune1|tune0|tune|selectat|select|reset|nudgeup|nudgedown|nudgeamount|input)",
                    "name": "support.variable.droid"
                },
                {
                    "match": "(output|ledup|leddown)",
                    "name": "support.other.variable.droid"
                },
                {
                    "include": "#basics"
                }
            ]
        },
        "inside_chord": {
            "patterns": [
                {
                    "match": "(tuningpitch|tuningmode|trigger|transpose|spread|selectfill5|selectfill4|selectfill3|selectfill2|selectfill1|select9|select7|select5|select3|select13|select11|select1|root|pitch|inversion|degree)",
                    "name": "support.variable.droid"
                },
                {
                    "match": "(output4|output3|output2|output1|output)",
                    "name": "support.other.variable.droid"
                },
                {
                    "include": "#basics"
                }
            ]
        },
        "inside_clocktool": {
            "patterns": [
                {
                    "match": "(reset|multiply|gatelength|dutycycle|divide|delay|clock)",
                    "name": "support.variable.droid"
                },
                {
                    "match": "(outputpitch|output|inputpitch)",
                    "name": "support.other.variable.droid"
                },
                {
                    "include": "#basics"
                }
            ]
        },
        "inside_compare": {
            "patterns": [
                {
                    "match": "(precision|input|ifless|ifgreater|ifequal|compare)",
                    "name": "support.variable.droid"
                },
                {
                    "match": "(output)",
                    "name": "support.other.variable.droid"
                },
                {
                    "include": "#basics"
                }
            ]
        },
        "inside_contour": {
            "patterns": [
                {
                    "match": "(zerocrossing|velocity|trigger|taptempo|swelltime|swellshape|swelllevel|swell|sustain|startfromzero|shape|retrigger|releaseshape|release|predelay|pitch|loop|level|hold|gate|decayshape|decay|attackshape|attack|abortattack)",
                    "name": "support.variable.droid"
                },
                {
                    "match": "(output|negated|inverted|endofrelease|endofpredelay|endofhold|endofdecay|endofattack)",
                    "name": "support.other.variable.droid"
                },
                {
                    "include": "#basics"
                }
            ]
        },
        "inside_copy": {
            "patterns": [
                {
                    "match": "(minimum|maximum|input)",
                    "name": "support.variable.droid"
                },
                {
                    "match": "(output|inverted)",
                    "name": "support.other.variable.droid"
                },
                {
                    "include": "#basics"
                }
            ]
        },
        "inside_crossfader": {
            "patterns": [
                {
                    "match": "(input8|input7|input6|input5|input4|input3|input2|input1|input|fade)",
                    "name": "support.variable.droid"
                },
                {
                    "match": "(output)",
                    "name": "support.other.variable.droid"
                },
                {
                    "include": "#basics"
                }
            ]
        },
        "inside_cvlooper": {
            "patterns": [
                {
                    "match": "(tapespeed|reset|pause|overlay|overdub|loopswitch|length|gatein|cvin|clock|bypass)",
                    "name": "support.variable.droid"
                },
                {
                    "match": "(gateout|cvout)",
                    "name": "support.other.variable.droid"
                },
                {
                    "include": "#basics"
                }
            ]
        },
        "inside_dac": {
            "patterns": [
                {
                    "match": "(minimum|maximum|bit9|bit8|bit7|bit6|bit5|bit4|bit3|bit2|bit12|bit11|bit10|bit1|bit)",
                    "name": "support.variable.droid"
                },
                {
                    "match": "(output)",
                    "name": "support.other.variable.droid"
                },
                {
                    "include": "#basics"
                }
            ]
        },
        "inside_droid": {
            "patterns": [
                {
                    "match": "(maxslope8|maxslope7|maxslope6|maxslope5|maxslope4|maxslope3|maxslope2|maxslope1|maxslope|lpfilter8|lpfilter7|lpfilter6|lpfilter5|lpfilter4|lpfilter3|lpfilter2|lpfilter1|lpfilter|ledbrightness)",
                    "name": "support.variable.droid"
                },
                {
                    "match": "(controllererrors)",
                    "name": "support.other.variable.droid"
                },
                {
                    "include": "#basics"
                }
            ]
        },
        "inside_euklid": {
            "patterns": [
                {
                    "match": "(reset|offset|length|clock|beats)",
                    "name": "support.variable.droid"
                },
                {
                    "match": "(output|offbeats)",
                    "name": "support.other.variable.droid"
                },
                {
                    "include": "#basics"
                }
            ]
        },
        "inside_explin": {
            "patterns": [
                {
                    "match": "(startvalue|mix|input|endvalue)",
                    "name": "support.variable.droid"
                },
                {
                    "match": "(output)",
                    "name": "support.other.variable.droid"
                },
                {
                    "include": "#basics"
                }
            ]
        },
        "inside_fold": {
            "patterns": [
                {
                    "match": "(minimum|maximum|input|foldby)",
                    "name": "support.variable.droid"
                },
                {
                    "match": "(output)",
                    "name": "support.other.variable.droid"
                },
                {
                    "include": "#basics"
                }
            ]
        },
        "inside_fourstatebutton": {
            "patterns": [
                {
                    "match": "(value4|value3|value2|value1|value|startvalue|reset|button)",
                    "name": "support.variable.droid"
                },
                {
                    "match": "(output|led)",
                    "name": "support.other.variable.droid"
                },
                {
                    "include": "#basics"
                }
            ]
        },
        "inside_lfo": {
            "patterns": [
                {
                    "match": "(waveform|taptempo|syncphase|sync|skew|rate|randomize|pulsewidth|phase|offset|level|hz|bipolar)",
                    "name": "support.variable.droid"
                },
                {
                    "match": "(triangle|square|sine|sawtooth|ramp|paraboloid|output|cosine)",
                    "name": "support.other.variable.droid"
                },
                {
                    "include": "#basics"
                }
            ]
        },
        "inside_logic": {
            "patterns": [
                {
                    "match": "(threshold|lowvalue|input8|input7|input6|input5|input4|input3|input2|input1|input|highvalue|countvalue)",
                    "name": "support.variable.droid"
                },
                {
                    "match": "(xor|or|nor|negated|nand|countlow|count|and)",
                    "name": "support.other.variable.droid"
                },
                {
                    "include": "#basics"
                }
            ]
        },
        "inside_math": {
            "patterns": [
                {
                    "match": "(input2|input1|input)",
                    "name": "support.variable.droid"
                },
                {
                    "match": "(sum|square|sine|round|root|reciprocal|quotient|product|power|negation|modulo|minimum|maximum|logarithm|floor|difference|cosine|ceil|average|amount)",
                    "name": "support.other.variable.droid"
                },
                {
                    "include": "#basics"
                }
            ]
        },
        "inside_matrixmixer": {
            "patterns": [
                {
                    "match": "(selectat|select|mixmax|input4|input3|input2|input1|input|button44|button43|button42|button41|button4|button34|button33|button32|button31|button3|button24|button23|button22|button21|button2|button14|button13|button12|button11|button1|auxin4|auxin3|auxin2|auxin1|auxin)",
                    "name": "support.variable.droid"
                },
                {
                    "match": "(output4|output3|output2|output1|output|led44|led43|led42|led41|led4|led34|led33|led32|led31|led3|led24|led23|led22|led21|led2|led14|led13|led12|led11|led1)",
                    "name": "support.other.variable.droid"
                },
                {
                    "include": "#basics"
                }
            ]
        },
        "inside_midifileplayer": {
            "patterns": [
                {
                    "match": "(voiceallocation|tuningpitch|tuningmode|transpose|track|speed|roundrobin|reset|pitchbendrange|note9|note8|note7|note6|note5|note4|note3|note2|note16|note15|note14|note13|note12|note11|note10|note1|note|lowestnote|loop|holdvelocity|highestnote|file|end|clock|channel|ccnumber4|ccnumber3|ccnumber2|ccnumber1|ccnumber|bendpitch)",
                    "name": "support.variable.droid"
                },
                {
                    "match": "(volume|velocity8|velocity7|velocity6|velocity5|velocity4|velocity3|velocity2|velocity1|velocity|trigger8|trigger7|trigger6|trigger5|trigger4|trigger3|trigger2|trigger1|trigger|programchange|program|pressure8|pressure7|pressure6|pressure5|pressure4|pressure3|pressure2|pressure1|pressure|pitchbend|pitch8|pitch7|pitch6|pitch5|pitch4|pitch3|pitch2|pitch1|pitch|notegate9|notegate8|notegate7|notegate6|notegate5|notegate4|notegate3|notegate2|notegate16|notegate15|notegate14|notegate13|notegate12|notegate11|notegate10|notegate1|notegate|modwheel|midiclock|gate8|gate7|gate6|gate5|gate4|gate3|gate2|gate1|gate|error|endoftrack|clockout|cc4|cc3|cc2|cc1|cc|bank)",
                    "name": "support.other.variable.droid"
                },
                {
                    "include": "#basics"
                }
            ]
        },
        "inside_midiin": {
            "patterns": [
                {
                    "match": "(voiceallocation|usb|tuningpitch|tuningmode|transpose|systemreset|roundrobin|pitchbendrange|note9|note8|note7|note6|note5|note4|note3|note2|note16|note15|note14|note13|note12|note11|note10|note1|note|lowestnote|holdvelocity|highestnote|channel|channel|ccnumber4|ccnumber3|ccnumber2|ccnumber1|ccnumber|bendpitch)",
                    "name": "support.variable.droid"
                },
                {
                    "match": "(volume|velocity8|velocity7|velocity6|velocity5|velocity4|velocity3|velocity2|velocity1|velocity|trigger8|trigger7|trigger6|trigger5|trigger4|trigger3|trigger2|trigger1|trigger|stop|start|running|programchange|program|pressure8|pressure7|pressure6|pressure5|pressure4|pressure3|pressure2|pressure1|pressure|pitchbend|pitch8|pitch7|pitch6|pitch5|pitch4|pitch3|pitch2|pitch1|pitch|notegate9|notegate8|notegate7|notegate6|notegate5|notegate4|notegate3|notegate2|notegate16|notegate15|notegate14|notegate13|notegate12|notegate11|notegate10|notegate1|notegate|modwheel|midiclock|gate8|gate7|gate6|gate5|gate4|gate3|gate2|gate1|gate|continue|clock8t|clock8|clock4|clock16|clock|cc4|cc3|cc2|cc1|cc|bank|active)",
                    "name": "support.other.variable.droid"
                },
                {
                    "include": "#basics"
                }
            ]
        },
        "inside_midiout": {
            "patterns": [
                {
                    "match": "(volume|velocity8|velocity7|velocity6|velocity5|velocity4|velocity3|velocity2|velocity1|velocity|usb|updaterate|triggerdelay|systemreset|stop|start|sostenuto|soft|running|programchange|program|pressure8|pressure7|pressure6|pressure5|pressure4|pressure3|pressure2|pressure1|pressure|portamento|pitchtracking|pitchstabilization|pitchbendrange|pitchbend|pitch8|pitch7|pitch6|pitch5|pitch4|pitch3|pitch2|pitch1|pitch|noteoffvelocity8|noteoffvelocity7|noteoffvelocity6|noteoffvelocity5|noteoffvelocity4|noteoffvelocity3|noteoffvelocity2|noteoffvelocity1|noteoffvelocity|notegatevelocity9|notegatevelocity8|notegatevelocity7|notegatevelocity6|notegatevelocity5|notegatevelocity4|notegatevelocity3|notegatevelocity2|notegatevelocity16|notegatevelocity15|notegatevelocity14|notegatevelocity13|notegatevelocity12|notegatevelocity11|notegatevelocity10|notegatevelocity1|notegatevelocity|notegate9|notegate8|notegate7|notegate6|notegate5|notegate4|notegate3|notegate2|notegate16|notegate15|notegate14|notegate13|notegate12|notegate11|notegate10|notegate1|notegate|note9|note8|note7|note6|note5|note4|note3|note2|note16|note15|note14|note13|note12|note11|note10|note1|note|modwheel|midiclock|lowestnote|legato|highestnote|gate8|gate7|gate6|gate5|gate4|gate3|gate2|gate1|gate|damper|clock|channelpressure|channel|ccnumber4|ccnumber3|ccnumber2|ccnumber1|ccnumber|cc4|cc3|cc2|cc1|cc|bank|allsoundoff|allnotesoff|activesensing)",
                    "name": "support.variable.droid"
                },
                {
                    "include": "#basics"
                }
            ]
        },
        "inside_midithrough": {
            "patterns": [
                {
                    "match": "(tousb|fromusb)",
                    "name": "support.variable.droid"
                },
                {
                    "include": "#basics"
                }
            ]
        },
        "inside_minifonion": {
            "patterns": [
                {
                    "match": "(tuningpitch|tuningmode|trigger|transpose|selectnoteshift|selectfill5|selectfill4|selectfill3|selectfill2|selectfill1|select9|select7|select5|select3|select13|select11|select1|root|noteshift|input|degree|bypass)",
                    "name": "support.variable.droid"
                },
                {
                    "match": "(output|notechange)",
                    "name": "support.other.variable.droid"
                },
                {
                    "include": "#basics"
                }
            ]
        },
        "inside_mixer": {
            "patterns": [
                {
                    "match": "(input8|input7|input6|input5|input4|input3|input2|input1|input)",
                    "name": "support.variable.droid"
                },
                {
                    "match": "(output|minimum|maximum|average)",
                    "name": "support.other.variable.droid"
                },
                {
                    "include": "#basics"
                }
            ]
        },
        "inside_motoquencer": {
            "patterns": [
                {
                    "match": "(tuningpitch|tuningmode|transpose|stepoffset|snapshot|selectfill5|selectfill4|selectfill3|selectfill2|selectfill1|selectat|select9|select7|select5|select3|select13|select11|select1|select|root|recall|quantize|pitchrange|pitchbase|fadermode|faderblock2|faderblock1|faderblock|degree|cvdefault3|cvdefault2|cvdefault1|cvdefault|clock|clear|buttonmode|bar|autoreset)",
                    "name": "support.variable.droid"
                },
                {
                    "match": "(pitch|gate3|gate2|gate1|gate|cv3|cv2|cv1|cv)",
                    "name": "support.other.variable.droid"
                },
                {
                    "include": "#basics"
                }
            ]
        },
        "inside_motorfader": {
            "patterns": [
                {
                    "match": "(startvalue|selectat|select|notches|fader|color|brightness|block)",
                    "name": "support.variable.droid"
                },
                {
                    "match": "(output)",
                    "name": "support.other.variable.droid"
                },
                {
                    "include": "#basics"
                }
            ]
        },
        "inside_notchedpot": {
            "patterns": [
                {
                    "match": "(pot|notch)",
                    "name": "support.variable.droid"
                },
                {
                    "match": "(righthalfinv|righthalf|output|lefthalfinv|lefthalf|bipolar|absbipolar)",
                    "name": "support.other.variable.droid"
                },
                {
                    "include": "#basics"
                }
            ]
        },
        "inside_notebuttons": {
            "patterns": [
                {
                    "match": "(selectat|select|clock|button9|button8|button7|button6|button5|button4|button3|button2|button12|button11|button10|button1|button)",
                    "name": "support.variable.droid"
                },
                {
                    "match": "(semitone|output|led9|led8|led7|led6|led5|led4|led3|led2|led12|led11|led10|led1|led)",
                    "name": "support.other.variable.droid"
                },
                {
                    "include": "#basics"
                }
            ]
        },
        "inside_nudge": {
            "patterns": [
                {
                    "match": "(wrap|startvalue|selectat|select|reset|persist|offset|minimum|maximum|buttonup|buttondown|amount)",
                    "name": "support.variable.droid"
                },
                {
                    "match": "(output|ledup|leddown)",
                    "name": "support.other.variable.droid"
                },
                {
                    "include": "#basics"
                }
            ]
        },
        "inside_octave": {
            "patterns": [
                {
                    "match": "(spread|input|fifths|detune)",
                    "name": "support.variable.droid"
                },
                {
                    "match": "(output3|output2|output1|output)",
                    "name": "support.other.variable.droid"
                },
                {
                    "include": "#basics"
                }
            ]
        },
        "inside_pot": {
            "patterns": [
                {
                    "match": "(slope|selectat|select|pot|outputscale|notch|ledgauge)",
                    "name": "support.variable.droid"
                },
                {
                    "match": "(righthalfinv|righthalf|output|onchange|lefthalfinv|lefthalf|bipolar|absbipolar)",
                    "name": "support.other.variable.droid"
                },
                {
                    "include": "#basics"
                }
            ]
        },
        "inside_quantizer": {
            "patterns": [
                {
                    "match": "(trigger|steps|input|bypass)",
                    "name": "support.variable.droid"
                },
                {
                    "match": "(output)",
                    "name": "support.other.variable.droid"
                },
                {
                    "include": "#basics"
                }
            ]
        },
        "inside_queue": {
            "patterns": [
                {
                    "match": "(outputpos8|outputpos7|outputpos6|outputpos5|outputpos4|outputpos3|outputpos2|outputpos1|outputpos|input|clock)",
                    "name": "support.variable.droid"
                },
                {
                    "match": "(output8|output7|output6|output5|output4|output3|output2|output1|output)",
                    "name": "support.other.variable.droid"
                },
                {
                    "include": "#basics"
                }
            ]
        },
        "inside_random": {
            "patterns": [
                {
                    "match": "(steps|minimum|maximum|clock)",
                    "name": "support.variable.droid"
                },
                {
                    "match": "(output)",
                    "name": "support.other.variable.droid"
                },
                {
                    "include": "#basics"
                }
            ]
        },
        "inside_sample": {
            "patterns": [
                {
                    "match": "(timewindow|sample|input|gate|bypass)",
                    "name": "support.variable.droid"
                },
                {
                    "match": "(output)",
                    "name": "support.other.variable.droid"
                },
                {
                    "include": "#basics"
                }
            ]
        },
        "inside_sequencer": {
            "patterns": [
                {
                    "match": "(transpose|steps|stages|slew8|slew7|slew6|slew5|slew4|slew3|slew2|slew1|slew|reset|repeat8|repeat7|repeat6|repeat5|repeat4|repeat3|repeat2|repeat1|repeat|pitch8|pitch7|pitch6|pitch5|pitch4|pitch3|pitch2|pitch1|pitch|outputscaling|gatelength|gate8|gate7|gate6|gate5|gate4|gate3|gate2|gate1|gate|cv8|cv7|cv6|cv5|cv4|cv3|cv2|cv1|cv|clock|chaintonext)",
                    "name": "support.variable.droid"
                },
                {
                    "match": "(pitchoutput|gateoutput|cvoutput)",
                    "name": "support.other.variable.droid"
                },
                {
                    "include": "#basics"
                }
            ]
        },
        "inside_slew": {
            "patterns": [
                {
                    "match": "(slewup|slewdown|slew|input|gate)",
                    "name": "support.variable.droid"
                },
                {
                    "match": "(scurve|linear|exponential)",
                    "name": "support.other.variable.droid"
                },
                {
                    "include": "#basics"
                }
            ]
        },
        "inside_spring": {
            "patterns": [
                {
                    "match": "(startvelocity|startposition|springforce|speed|shoveforce|shove|reset|mass|gravity|friction|flowresistance)",
                    "name": "support.variable.droid"
                },
                {
                    "match": "(velocity|position)",
                    "name": "support.other.variable.droid"
                },
                {
                    "include": "#basics"
                }
            ]
        },
        "inside_superjust": {
            "patterns": [
                {
                    "match": "(tuningpitch|tuningmode|transpose|input8|input7|input6|input5|input4|input3|input2|input1|input|bypass)",
                    "name": "support.variable.droid"
                },
                {
                    "match": "(output8|output7|output6|output5|output4|output3|output2|output1|output)",
                    "name": "support.other.variable.droid"
                },
                {
                    "include": "#basics"
                }
            ]
        },
        "inside_switch": {
            "patterns": [
                {
                    "match": "(reset|offset|input8|input7|input6|input5|input4|input3|input2|input1|input|forward|backward)",
                    "name": "support.variable.droid"
                },
                {
                    "match": "(output8|output7|output6|output5|output4|output3|output2|output1|output)",
                    "name": "support.other.variable.droid"
                },
                {
                    "include": "#basics"
                }
            ]
        },
        "inside_switchedpot": {
            "patterns": [
                {
                    "match": "(switch8|switch7|switch6|switch5|switch4|switch3|switch2|switch1|switch|pot|bipolar)",
                    "name": "support.variable.droid"
                },
                {
                    "match": "(output8|output7|output6|output5|output4|output3|output2|output1|output)",
                    "name": "support.other.variable.droid"
                },
                {
                    "include": "#basics"
                }
            ]
        },
        "inside_timing": {
            "patterns": [
                {
                    "match": "(timing8|timing7|timing6|timing5|timing4|timing3|timing2|timing1|timing|reset|clock)",
                    "name": "support.variable.droid"
                },
                {
                    "match": "(output)",
                    "name": "support.other.variable.droid"
                },
                {
                    "include": "#basics"
                }
            ]
        },
        "inside_togglebutton": {
            "patterns": [
                {
                    "match": "(switch|startvalue|reset4|reset3|reset2|reset1|reset|onvalue|offvalue|doubleclickmode|button)",
                    "name": "support.variable.droid"
                },
                {
                    "match": "(output4|output3|output2|output1|output|negated|led|inverted)",
                    "name": "support.other.variable.droid"
                },
                {
                    "include": "#basics"
                }
            ]
        },
        "inside_transient": {
            "patterns": [
                {
                    "match": "(start|reset|pingpong|loop|freeze|end|duration|clock)",
                    "name": "support.variable.droid"
                },
                {
                    "match": "(phase|output|endoftransient)",
                    "name": "support.other.variable.droid"
                },
                {
                    "include": "#basics"
                }
            ]
        },
        "inside_triggerdelay": {
            "patterns": [
                {
                    "match": "(repeats|mute|input|gatelength|delay|clock)",
                    "name": "support.variable.droid"
                },
                {
                    "match": "(overflow|output)",
                    "name": "support.other.variable.droid"
                },
                {
                    "include": "#basics"
                }
            ]
        },
        "lfo": {
            "patterns": [
                {
                    "begin": "(\\[lfo\\])",
                    "beginCaptures": {
                        "1": {
                            "name": "support.class.droid"
                        }
                    },
                    "patterns": [
                        {
                            "include": "#inside_lfo"
                        }
                    ],
                    "end": "(?=\\[)",
                    "endCaptures": {
                        "1": {
                            "name": "support.class.droid"
                        }
                    }
                }
            ]
        },
        "logic": {
            "patterns": [
                {
                    "begin": "(\\[logic\\])",
                    "beginCaptures": {
                        "1": {
                            "name": "support.class.droid"
                        }
                    },
                    "patterns": [
                        {
                            "include": "#inside_logic"
                        }
                    ],
                    "end": "(?=\\[)",
                    "endCaptures": {
                        "1": {
                            "name": "support.class.droid"
                        }
                    }
                }
            ]
        },
        "math": {
            "patterns": [
                {
                    "begin": "(\\[math\\])",
                    "beginCaptures": {
                        "1": {
                            "name": "support.class.droid"
                        }
                    },
                    "patterns": [
                        {
                            "include": "#inside_math"
                        }
                    ],
                    "end": "(?=\\[)",
                    "endCaptures": {
                        "1": {
                            "name": "support.class.droid"
                        }
                    }
                }
            ]
        },
        "matrixmixer": {
            "patterns": [
                {
                    "begin": "(\\[matrixmixer\\])",
                    "beginCaptures": {
                        "1": {
                            "name": "support.class.droid"
                        }
                    },
                    "patterns": [
                        {
                            "include": "#inside_matrixmixer"
                        }
                    ],
                    "end": "(?=\\[)",
                    "endCaptures": {
                        "1": {
                            "name": "support.class.droid"
                        }
                    }
                }
            ]
        },
        "midifileplayer": {
            "patterns": [
                {
                    "begin": "(\\[midifileplayer\\])",
                    "beginCaptures": {
                        "1": {
                            "name": "support.class.droid"
                        }
                    },
                    "patterns": [
                        {
                            "include": "#inside_midifileplayer"
                        }
                    ],
                    "end": "(?=\\[)",
                    "endCaptures": {
                        "1": {
                            "name": "support.class.droid"
                        }
                    }
                }
            ]
        },
        "midiin": {
            "patterns": [
                {
                    "begin": "(\\[midiin\\])",
                    "beginCaptures": {
                        "1": {
                            "name": "support.class.droid"
                        }
                    },
                    "patterns": [
                        {
                            "include": "#inside_midiin"
                        }
                    ],
                    "end": "(?=\\[)",
                    "endCaptures": {
                        "1": {
                            "name": "support.class.droid"
                        }
                    }
                }
            ]
        },
        "midiout": {
            "patterns": [
                {
                    "begin": "(\\[midiout\\])",
                    "beginCaptures": {
                        "1": {
                            "name": "support.class.droid"
                        }
                    },
                    "patterns": [
                        {
                            "include": "#inside_midiout"
                        }
                    ],
                    "end": "(?=\\[)",
                    "endCaptures": {
                        "1": {
                            "name": "support.class.droid"
                        }
                    }
                }
            ]
        },
        "midithrough": {
            "patterns": [
                {
                    "begin": "(\\[midithrough\\])",
                    "beginCaptures": {
                        "1": {
                            "name": "support.class.droid"
                        }
                    },
                    "patterns": [
                        {
                            "include": "#inside_midithrough"
                        }
                    ],
                    "end": "(?=\\[)",
                    "endCaptures": {
                        "1": {
                            "name": "support.class.droid"
                        }
                    }
                }
            ]
        },
        "minifonion": {
            "patterns": [
                {
                    "begin": "(\\[minifonion\\])",
                    "beginCaptures": {
                        "1": {
                            "name": "support.class.droid"
                        }
                    },
                    "patterns": [
                        {
                            "include": "#inside_minifonion"
                        }
                    ],
                    "end": "(?=\\[)",
                    "endCaptures": {
                        "1": {
                            "name": "support.class.droid"
                        }
                    }
                }
            ]
        },
        "mixer": {
            "patterns": [
                {
                    "begin": "(\\[mixer\\])",
                    "beginCaptures": {
                        "1": {
                            "name": "support.class.droid"
                        }
                    },
                    "patterns": [
                        {
                            "include": "#inside_mixer"
                        }
                    ],
                    "end": "(?=\\[)",
                    "endCaptures": {
                        "1": {
                            "name": "support.class.droid"
                        }
                    }
                }
            ]
        },
        "motoquencer": {
            "patterns": [
                {
                    "begin": "(\\[motoquencer\\])",
                    "beginCaptures": {
                        "1": {
                            "name": "support.class.droid"
                        }
                    },
                    "patterns": [
                        {
                            "include": "#inside_motoquencer"
                        }
                    ],
                    "end": "(?=\\[)",
                    "endCaptures": {
                        "1": {
                            "name": "support.class.droid"
                        }
                    }
                }
            ]
        },
        "motorfader": {
            "patterns": [
                {
                    "begin": "(\\[motorfader\\])",
                    "beginCaptures": {
                        "1": {
                            "name": "support.class.droid"
                        }
                    },
                    "patterns": [
                        {
                            "include": "#inside_motorfader"
                        }
                    ],
                    "end": "(?=\\[)",
                    "endCaptures": {
                        "1": {
                            "name": "support.class.droid"
                        }
                    }
                }
            ]
        },
        "notchedpot": {
            "patterns": [
                {
                    "begin": "(\\[notchedpot\\])",
                    "beginCaptures": {
                        "1": {
                            "name": "support.class.droid"
                        }
                    },
                    "patterns": [
                        {
                            "include": "#inside_notchedpot"
                        }
                    ],
                    "end": "(?=\\[)",
                    "endCaptures": {
                        "1": {
                            "name": "support.class.droid"
                        }
                    }
                }
            ]
        },
        "notebuttons": {
            "patterns": [
                {
                    "begin": "(\\[notebuttons\\])",
                    "beginCaptures": {
                        "1": {
                            "name": "support.class.droid"
                        }
                    },
                    "patterns": [
                        {
                            "include": "#inside_notebuttons"
                        }
                    ],
                    "end": "(?=\\[)",
                    "endCaptures": {
                        "1": {
                            "name": "support.class.droid"
                        }
                    }
                }
            ]
        },
        "nudge": {
            "patterns": [
                {
                    "begin": "(\\[nudge\\])",
                    "beginCaptures": {
                        "1": {
                            "name": "support.class.droid"
                        }
                    },
                    "patterns": [
                        {
                            "include": "#inside_nudge"
                        }
                    ],
                    "end": "(?=\\[)",
                    "endCaptures": {
                        "1": {
                            "name": "support.class.droid"
                        }
                    }
                }
            ]
        },
        "octave": {
            "patterns": [
                {
                    "begin": "(\\[octave\\])",
                    "beginCaptures": {
                        "1": {
                            "name": "support.class.droid"
                        }
                    },
                    "patterns": [
                        {
                            "include": "#inside_octave"
                        }
                    ],
                    "end": "(?=\\[)",
                    "endCaptures": {
                        "1": {
                            "name": "support.class.droid"
                        }
                    }
                }
            ]
        },
        "pot": {
            "patterns": [
                {
                    "begin": "(\\[pot\\])",
                    "beginCaptures": {
                        "1": {
                            "name": "support.class.droid"
                        }
                    },
                    "patterns": [
                        {
                            "include": "#inside_pot"
                        }
                    ],
                    "end": "(?=\\[)",
                    "endCaptures": {
                        "1": {
                            "name": "support.class.droid"
                        }
                    }
                }
            ]
        },
        "quantizer": {
            "patterns": [
                {
                    "begin": "(\\[quantizer\\])",
                    "beginCaptures": {
                        "1": {
                            "name": "support.class.droid"
                        }
                    },
                    "patterns": [
                        {
                            "include": "#inside_quantizer"
                        }
                    ],
                    "end": "(?=\\[)",
                    "endCaptures": {
                        "1": {
                            "name": "support.class.droid"
                        }
                    }
                }
            ]
        },
        "queue": {
            "patterns": [
                {
                    "begin": "(\\[queue\\])",
                    "beginCaptures": {
                        "1": {
                            "name": "support.class.droid"
                        }
                    },
                    "patterns": [
                        {
                            "include": "#inside_queue"
                        }
                    ],
                    "end": "(?=\\[)",
                    "endCaptures": {
                        "1": {
                            "name": "support.class.droid"
                        }
                    }
                }
            ]
        },
        "random": {
            "patterns": [
                {
                    "begin": "(\\[random\\])",
                    "beginCaptures": {
                        "1": {
                            "name": "support.class.droid"
                        }
                    },
                    "patterns": [
                        {
                            "include": "#inside_random"
                        }
                    ],
                    "end": "(?=\\[)",
                    "endCaptures": {
                        "1": {
                            "name": "support.class.droid"
                        }
                    }
                }
            ]
        },
        "sample": {
            "patterns": [
                {
                    "begin": "(\\[sample\\])",
                    "beginCaptures": {
                        "1": {
                            "name": "support.class.droid"
                        }
                    },
                    "patterns": [
                        {
                            "include": "#inside_sample"
                        }
                    ],
                    "end": "(?=\\[)",
                    "endCaptures": {
                        "1": {
                            "name": "support.class.droid"
                        }
                    }
                }
            ]
        },
        "sequencer": {
            "patterns": [
                {
                    "begin": "(\\[sequencer\\])",
                    "beginCaptures": {
                        "1": {
                            "name": "support.class.droid"
                        }
                    },
                    "patterns": [
                        {
                            "include": "#inside_sequencer"
                        }
                    ],
                    "end": "(?=\\[)",
                    "endCaptures": {
                        "1": {
                            "name": "support.class.droid"
                        }
                    }
                }
            ]
        },
        "slew": {
            "patterns": [
                {
                    "begin": "(\\[slew\\])",
                    "beginCaptures": {
                        "1": {
                            "name": "support.class.droid"
                        }
                    },
                    "patterns": [
                        {
                            "include": "#inside_slew"
                        }
                    ],
                    "end": "(?=\\[)",
                    "endCaptures": {
                        "1": {
                            "name": "support.class.droid"
                        }
                    }
                }
            ]
        },
        "spring": {
            "patterns": [
                {
                    "begin": "(\\[spring\\])",
                    "beginCaptures": {
                        "1": {
                            "name": "support.class.droid"
                        }
                    },
                    "patterns": [
                        {
                            "include": "#inside_spring"
                        }
                    ],
                    "end": "(?=\\[)",
                    "endCaptures": {
                        "1": {
                            "name": "support.class.droid"
                        }
                    }
                }
            ]
        },
        "superjust": {
            "patterns": [
                {
                    "begin": "(\\[superjust\\])",
                    "beginCaptures": {
                        "1": {
                            "name": "support.class.droid"
                        }
                    },
                    "patterns": [
                        {
                            "include": "#inside_superjust"
                        }
                    ],
                    "end": "(?=\\[)",
                    "endCaptures": {
                        "1": {
                            "name": "support.class.droid"
                        }
                    }
                }
            ]
        },
        "switch": {
            "patterns": [
                {
                    "begin": "(\\[switch\\])",
                    "beginCaptures": {
                        "1": {
                            "name": "support.class.droid"
                        }
                    },
                    "patterns": [
                        {
                            "include": "#inside_switch"
                        }
                    ],
                    "end": "(?=\\[)",
                    "endCaptures": {
                        "1": {
                            "name": "support.class.droid"
                        }
                    }
                }
            ]
        },
        "switchedpot": {
            "patterns": [
                {
                    "begin": "(\\[switchedpot\\])",
                    "beginCaptures": {
                        "1": {
                            "name": "support.class.droid"
                        }
                    },
                    "patterns": [
                        {
                            "include": "#inside_switchedpot"
                        }
                    ],
                    "end": "(?=\\[)",
                    "endCaptures": {
                        "1": {
                            "name": "support.class.droid"
                        }
                    }
                }
            ]
        },
        "timing": {
            "patterns": [
                {
                    "begin": "(\\[timing\\])",
                    "beginCaptures": {
                        "1": {
                            "name": "support.class.droid"
                        }
                    },
                    "patterns": [
                        {
                            "include": "#inside_timing"
                        }
                    ],
                    "end": "(?=\\[)",
                    "endCaptures": {
                        "1": {
                            "name": "support.class.droid"
                        }
                    }
                }
            ]
        },
        "togglebutton": {
            "patterns": [
                {
                    "begin": "(\\[togglebutton\\])",
                    "beginCaptures": {
                        "1": {
                            "name": "support.class.droid"
                        }
                    },
                    "patterns": [
                        {
                            "include": "#inside_togglebutton"
                        }
                    ],
                    "end": "(?=\\[)",
                    "endCaptures": {
                        "1": {
                            "name": "support.class.droid"
                        }
                    }
                }
            ]
        },
        "transient": {
            "patterns": [
                {
                    "begin": "(\\[transient\\])",
                    "beginCaptures": {
                        "1": {
                            "name": "support.class.droid"
                        }
                    },
                    "patterns": [
                        {
                            "include": "#inside_transient"
                        }
                    ],
                    "end": "(?=\\[)",
                    "endCaptures": {
                        "1": {
                            "name": "support.class.droid"
                        }
                    }
                }
            ]
        },
        "triggerdelay": {
            "patterns": [
                {
                    "begin": "(\\[triggerdelay\\])",
                    "beginCaptures": {
                        "1": {
                            "name": "support.class.droid"
                        }
                    },
                    "patterns": [
                        {
                            "include": "#inside_triggerdelay"
                        }
                    ],
                    "end": "(?=\\[)",
                    "endCaptures": {
                        "1": {
                            "name": "support.class.droid"
                        }
                    }
                }
            ]
        }
    }
}